{
  "hits": [
    {
      "frame_number": 194,
      "player_unique_id": "76561198784847286"
    },
    {
      "frame_number": 195,
      "player_unique_id": "f68265d5ce0848dd8ad15f078c427b02"
    },
    {
      "frame_number": 262,
      "player_unique_id": "76561198784847286"
    },
    {
      "frame_number": 312,
      "player_unique_id": "76561198784847286"
    },
    {
      "frame_number": 315,
      "player_unique_id": "f68265d5ce0848dd8ad15f078c427b02"
    },
    {
      "frame_number": 376,
      "player_unique_id": "f68265d5ce0848dd8ad15f078c427b02"
    },
    {
      "frame_number": 422,
      "player_unique_id": "f68265d5ce0848dd8ad15f078c427b02"
    },
    {
      "frame_number": 720,
      "player_unique_id": "f68265d5ce0848dd8ad15f078c427b02"
    },
    {
      "frame_number": 786,
      "player_unique_id": "f68265d5ce0848dd8ad15f078c427b02"
    },
    {
      "frame_number": 1154,
      "player_unique_id": "f68265d5ce0848dd8ad15f078c427b02"
    },
    {
      "frame_number": 1156,
      "player_unique_id": "76561198784847286"
    },
    {
      "frame_number": 1157,
      "player_unique_id": "f68265d5ce0848dd8ad15f078c427b02"
    },
    {
      "frame_number": 1220,
      "player_unique_id": "76561198784847286"
    },
    {
      "frame_number": 1304,
      "player_unique_id": "76561198784847286"
    },
    {
      "frame_number": 1339,
      "player_unique_id": "76561198784847286"
    },
    {
      "frame_number": 1507,
      "player_unique_id": "f68265d5ce0848dd8ad15f078c427b02"
    },
    {
      "frame_number": 1559,
      "player_unique_id": "76561198784847286"
    },
    {
      "frame_number": 1585,
      "player_unique_id": "76561198784847286"
    },
    {
      "frame_number": 1635,
      "player_unique_id": "76561198784847286"
    },
    {
      "frame_number": 1915,
      "player_unique_id": "f68265d5ce0848dd8ad15f078c427b02"
    },
    {
      "frame_number": 1917,
      "player_unique_id": "76561198784847286"
    },
    {
      "frame_number": 1920,
      "player_unique_id": "f68265d5ce0848dd8ad15f078c427b02"
    },
    {
      "frame_number": 1959,
      "player_unique_id": "76561198784847286"
    },
    {
      "frame_number": 2075,
      "player_unique_id": "76561198784847286"
    },
    {
      "frame_number": 2096,
      "player_unique_id": "76561198784847286"
    },
    {
      "frame_number": 2128,
      "player_unique_id": "76561198784847286"
    },
    {
      "frame_number": 2168,
      "player_unique_id": "76561198784847286"
    },
    {
      "frame_number": 2242,
      "player_unique_id": "f68265d5ce0848dd8ad15f078c427b02"
    },
    {
      "frame_number": 2328,
      "player_unique_id": "f68265d5ce0848dd8ad15f078c427b02"
    },
    {
      "frame_number": 2405,
      "player_unique_id": "76561198784847286"
    },
    {
      "frame_number": 2481,
      "player_unique_id": "76561198784847286"
    },
    {
      "frame_number": 2538,
      "player_unique_id": "76561198784847286"
    },
    {
      "frame_number": 2554,
      "player_unique_id": "76561198784847286"
    },
    {
      "frame_number": 2572,
      "player_unique_id": "76561198784847286"
    },
    {
      "frame_number": 2580,
      "player_unique_id": "76561198784847286"
    },
    {
      "frame_number": 2594,
      "player_unique_id": "76561198784847286"
    },
    {
      "frame_number": 2691,
      "player_unique_id": "f68265d5ce0848dd8ad15f078c427b02"
    },
    {
      "frame_number": 2748,
      "player_unique_id": "76561198784847286"
    },
    {
      "frame_number": 3071,
      "player_unique_id": "f68265d5ce0848dd8ad15f078c427b02"
    },
    {
      "frame_number": 3175,
      "player_unique_id": "f68265d5ce0848dd8ad15f078c427b02"
    },
    {
      "frame_number": 3463,
      "player_unique_id": "f68265d5ce0848dd8ad15f078c427b02"
    },
    {
      "frame_number": 3464,
      "player_unique_id": "76561198784847286"
    },
    {
      "frame_number": 3465,
      "player_unique_id": "f68265d5ce0848dd8ad15f078c427b02"
    },
    {
      "frame_number": 3466,
      "player_unique_id": "76561198784847286"
    },
    {
      "frame_number": 3467,
      "player_unique_id": "f68265d5ce0848dd8ad15f078c427b02"
    },
    {
      "frame_number": 3579,
      "player_unique_id": "76561198784847286"
    },
    {
      "frame_number": 3637,
      "player_unique_id": "f68265d5ce0848dd8ad15f078c427b02"
    },
    {
      "frame_number": 3659,
      "player_unique_id": "76561198784847286"
    },
    {
      "frame_number": 3716,
      "player_unique_id": "76561198784847286"
    },
    {
      "frame_number": 3810,
      "player_unique_id": "f68265d5ce0848dd8ad15f078c427b02"
    },
    {
      "frame_number": 3908,
      "player_unique_id": "f68265d5ce0848dd8ad15f078c427b02"
    },
    {
      "frame_number": 4215,
      "player_unique_id": "f68265d5ce0848dd8ad15f078c427b02"
    },
    {
      "frame_number": 4216,
      "player_unique_id": "76561198784847286"
    },
    {
      "frame_number": 4217,
      "player_unique_id": "f68265d5ce0848dd8ad15f078c427b02"
    },
    {
      "frame_number": 4307,
      "player_unique_id": "f68265d5ce0848dd8ad15f078c427b02"
    },
    {
      "frame_number": 4364,
      "player_unique_id": "76561198784847286"
    },
    {
      "frame_number": 4448,
      "player_unique_id": "f68265d5ce0848dd8ad15f078c427b02"
    },
    {
      "frame_number": 4453,
      "player_unique_id": "76561198784847286"
    },
    {
      "frame_number": 4531,
      "player_unique_id": "76561198784847286"
    },
    {
      "frame_number": 4558,
      "player_unique_id": "76561198784847286"
    },
    {
      "frame_number": 4581,
      "player_unique_id": "76561198784847286"
    },
    {
      "frame_number": 4582,
      "player_unique_id": "76561198784847286"
    },
    {
      "frame_number": 4666,
      "player_unique_id": "f68265d5ce0848dd8ad15f078c427b02"
    },
    {
      "frame_number": 4762,
      "player_unique_id": "76561198784847286"
    },
    {
      "frame_number": 4822,
      "player_unique_id": "76561198784847286"
    },
    {
      "frame_number": 4900,
      "player_unique_id": "76561198784847286"
    },
    {
      "frame_number": 4916,
      "player_unique_id": "76561198784847286"
    },
    {
      "frame_number": 4937,
      "player_unique_id": "76561198784847286"
    },
    {
      "frame_number": 4946,
      "player_unique_id": "76561198784847286"
    },
    {
      "frame_number": 4960,
      "player_unique_id": "76561198784847286"
    },
    {
      "frame_number": 4963,
      "player_unique_id": "76561198784847286"
    },
    {
      "frame_number": 4982,
      "player_unique_id": "76561198784847286"
    },
    {
      "frame_number": 4984,
      "player_unique_id": "76561198784847286"
    },
    {
      "frame_number": 4996,
      "player_unique_id": "76561198784847286"
    },
    {
      "frame_number": 5112,
      "player_unique_id": "76561198784847286"
    },
    {
      "frame_number": 5122,
      "player_unique_id": "76561198784847286"
    },
    {
      "frame_number": 5134,
      "player_unique_id": "76561198784847286"
    },
    {
      "frame_number": 5149,
      "player_unique_id": "76561198784847286"
    },
    {
      "frame_number": 5187,
      "player_unique_id": "76561198784847286"
    },
    {
      "frame_number": 5198,
      "player_unique_id": "76561198784847286"
    },
    {
      "frame_number": 5231,
      "player_unique_id": "76561198784847286"
    },
    {
      "frame_number": 5233,
      "player_unique_id": "76561198784847286"
    },
    {
      "frame_number": 5234,
      "player_unique_id": "f68265d5ce0848dd8ad15f078c427b02"
    },
    {
      "frame_number": 5274,
      "player_unique_id": "76561198784847286"
    },
    {
      "frame_number": 5278,
      "player_unique_id": "76561198784847286"
    },
    {
      "frame_number": 5314,
      "player_unique_id": "76561198784847286"
    },
    {
      "frame_number": 5428,
      "player_unique_id": "76561198784847286"
    },
    {
      "frame_number": 5454,
      "player_unique_id": "76561198784847286"
    },
    {
      "frame_number": 5484,
      "player_unique_id": "76561198784847286"
    },
    {
      "frame_number": 5505,
      "player_unique_id": "76561198784847286"
    },
    {
      "frame_number": 5535,
      "player_unique_id": "76561198784847286"
    },
    {
      "frame_number": 5594,
      "player_unique_id": "f68265d5ce0848dd8ad15f078c427b02"
    },
    {
      "frame_number": 5690,
      "player_unique_id": "f68265d5ce0848dd8ad15f078c427b02"
    },
    {
      "frame_number": 6058,
      "player_unique_id": "f68265d5ce0848dd8ad15f078c427b02"
    },
    {
      "frame_number": 6138,
      "player_unique_id": "76561198784847286"
    },
    {
      "frame_number": 6224,
      "player_unique_id": "76561198784847286"
    },
    {
      "frame_number": 6300,
      "player_unique_id": "f68265d5ce0848dd8ad15f078c427b02"
    },
    {
      "frame_number": 6322,
      "player_unique_id": "f68265d5ce0848dd8ad15f078c427b02"
    },
    {
      "frame_number": 6330,
      "player_unique_id": "f68265d5ce0848dd8ad15f078c427b02"
    },
    {
      "frame_number": 6343,
      "player_unique_id": "f68265d5ce0848dd8ad15f078c427b02"
    },
    {
      "frame_number": 6662,
      "player_unique_id": "f68265d5ce0848dd8ad15f078c427b02"
    },
    {
      "frame_number": 6663,
      "player_unique_id": "76561198784847286"
    },
    {
      "frame_number": 6664,
      "player_unique_id": "f68265d5ce0848dd8ad15f078c427b02"
    },
    {
      "frame_number": 6741,
      "player_unique_id": "76561198784847286"
    },
    {
      "frame_number": 6873,
      "player_unique_id": "76561198784847286"
    },
    {
      "frame_number": 6879,
      "player_unique_id": "76561198784847286"
    },
    {
      "frame_number": 7235,
      "player_unique_id": "f68265d5ce0848dd8ad15f078c427b02"
    },
    {
      "frame_number": 7341,
      "player_unique_id": "f68265d5ce0848dd8ad15f078c427b02"
    },
    {
      "frame_number": 7500,
      "player_unique_id": "76561198784847286"
    },
    {
      "frame_number": 7502,
      "player_unique_id": "76561198784847286"
    },
    {
      "frame_number": 7517,
      "player_unique_id": "76561198784847286"
    },
    {
      "frame_number": 7537,
      "player_unique_id": "76561198784847286"
    },
    {
      "frame_number": 7547,
      "player_unique_id": "76561198784847286"
    },
    {
      "frame_number": 7559,
      "player_unique_id": "76561198784847286"
    },
    {
      "frame_number": 7575,
      "player_unique_id": "76561198784847286"
    },
    {
      "frame_number": 7583,
      "player_unique_id": "76561198784847286"
    },
    {
      "frame_number": 7597,
      "player_unique_id": "76561198784847286"
    },
    {
      "frame_number": 7622,
      "player_unique_id": "f68265d5ce0848dd8ad15f078c427b02"
    },
    {
      "frame_number": 7717,
      "player_unique_id": "f68265d5ce0848dd8ad15f078c427b02"
    },
    {
      "frame_number": 7768,
      "player_unique_id": "f68265d5ce0848dd8ad15f078c427b02"
    },
    {
      "frame_number": 7782,
      "player_unique_id": "f68265d5ce0848dd8ad15f078c427b02"
    },
    {
      "frame_number": 7844,
      "player_unique_id": "f68265d5ce0848dd8ad15f078c427b02"
    },
    {
      "frame_number": 8137,
      "player_unique_id": "f68265d5ce0848dd8ad15f078c427b02"
    },
    {
      "frame_number": 8140,
      "player_unique_id": "76561198784847286"
    },
    {
      "frame_number": 8142,
      "player_unique_id": "f68265d5ce0848dd8ad15f078c427b02"
    },
    {
      "frame_number": 8305,
      "player_unique_id": "f68265d5ce0848dd8ad15f078c427b02"
    },
    {
      "frame_number": 8316,
      "player_unique_id": "f68265d5ce0848dd8ad15f078c427b02"
    },
    {
      "frame_number": 8323,
      "player_unique_id": "f68265d5ce0848dd8ad15f078c427b02"
    },
    {
      "frame_number": 8335,
      "player_unique_id": "f68265d5ce0848dd8ad15f078c427b02"
    },
    {
      "frame_number": 8348,
      "player_unique_id": "f68265d5ce0848dd8ad15f078c427b02"
    },
    {
      "frame_number": 8355,
      "player_unique_id": "f68265d5ce0848dd8ad15f078c427b02"
    },
    {
      "frame_number": 8373,
      "player_unique_id": "f68265d5ce0848dd8ad15f078c427b02"
    },
    {
      "frame_number": 8382,
      "player_unique_id": "f68265d5ce0848dd8ad15f078c427b02"
    },
    {
      "frame_number": 8476,
      "player_unique_id": "f68265d5ce0848dd8ad15f078c427b02"
    }
  ],
  "gameplay_periods": [
    {
      "start_frame": 119,
      "goal_frame": 443
    },
    {
      "start_frame": 652,
      "goal_frame": 871
    },
    {
      "start_frame": 1080,
      "goal_frame": 1647
    },
    {
      "start_frame": 1857,
      "goal_frame": 2807
    },
    {
      "start_frame": 3017,
      "goal_frame": 3191
    },
    {
      "start_frame": 3398,
      "goal_frame": 3938
    },
    {
      "start_frame": 4148,
      "goal_frame": 5773
    },
    {
      "start_frame": 5983,
      "goal_frame": 6392
    },
    {
      "start_frame": 6602,
      "goal_frame": 6967
    },
    {
      "start_frame": 7176,
      "goal_frame": 7860
    },
    {
      "start_frame": 8070,
      "goal_frame": 8500
    }
  ]
}